<?xml version="1.0" encoding="UTF-8"?>
<objects serializationModel="Studio.02.02.00">
	<object class="AudioFile" id="{8e657181-9267-43dc-9be9-4b57e192b4a2}">
		<property name="assetPath">
			<value>Sound Effects/Footsteps/FootstepSFX_04.wav</value>
		</property>
		<property name="frequencyInKHz">
			<value>44.0999985</value>
		</property>
		<property name="channelCount">
			<value>2</value>
		</property>
		<property name="length">
			<value>0.29523809523809524</value>
		</property>
		<relationship name="masterAssetFolder">
			<destination>{36e5cab1-617d-484c-b069-c89b012812a1}</destination>
		</relationship>
	</object>
</objects>
